word2keypress/__init__.py
word2keypress/_keyboard.c
word2keypress/_keyboard.so
word2keypress/adjacency_graphs.py
word2keypress/weight_matrix.py
word2keypress/weighted_edist.py
word2keypress-1.0.10.dist-info/DESCRIPTION.rst
word2keypress-1.0.10.dist-info/LICENSE.txt
word2keypress-1.0.10.dist-info/METADATA
word2keypress-1.0.10.dist-info/RECORD
word2keypress-1.0.10.dist-info/WHEEL
word2keypress-1.0.10.dist-info/metadata.json
word2keypress-1.0.10.dist-info/top_level.txt
