Metadata-Version: 2.0
Name: word2keypress
Version: 1.0.10
Summary: Convert word to keypress sequence
Home-page: https://github.com/rchatterjee/word2keypress.git
Author: Rahul Chatterjee
Author-email: rahul@cs.cornell.edu
License: MIT License
Platform: UNKNOWN
Classifier: Development Status :: 3 - Alpha
Classifier: Topic :: Utilities
Classifier: License :: OSI Approved :: MIT License
